{
  "ts": "2026-07-07T21:07:44.129Z",
  "overall": "up",
  "results": [
    {
      "id": "co-www-home",
      "name": "Storefront home",
      "url": "https://www.catholicowned.com/us",
      "state": "up",
      "status": 200,
      "ttfb": 932,
      "total": 946,
      "edge": "iad1",
      "warnMs": 3000,
      "service": "Catholic Owned — Production"
    },
    {
      "id": "co-www-directory",
      "name": "Directory",
      "url": "https://www.catholicowned.com/us/directory",
      "state": "up",
      "status": 200,
      "ttfb": 805,
      "total": 821,
      "edge": "iad1",
      "warnMs": 3000,
      "service": "Catholic Owned — Production"
    },
    {
      "id": "co-api-health",
      "name": "Backend API /health",
      "url": "https://api.catholicowned.com/health",
      "state": "up",
      "status": 200,
      "ttfb": 259,
      "total": 259,
      "edge": "iad1",
      "warnMs": 1500,
      "service": "Catholic Owned — Production"
    },
    {
      "id": "co-admin",
      "name": "Admin dashboard",
      "url": "https://v3-admin.catholicowned.com/",
      "state": "up",
      "status": 200,
      "ttfb": 361,
      "total": 362,
      "edge": "iad1",
      "warnMs": 2000,
      "service": "Catholic Owned — Production"
    },
    {
      "id": "co-vendor",
      "name": "Vendor dashboard",
      "url": "https://v3-vendor.catholicowned.com/",
      "state": "up",
      "status": 200,
      "ttfb": 252,
      "total": 254,
      "edge": "iad1",
      "warnMs": 2000,
      "service": "Catholic Owned — Production"
    },
    {
      "id": "co-cdn",
      "name": "Media CDN (minio)",
      "url": "https://v3-cdn.catholicowned.com/",
      "state": "up",
      "status": 403,
      "ttfb": 388,
      "total": 388,
      "edge": "iad1",
      "warnMs": 3000,
      "service": "Catholic Owned — Production"
    },
    {
      "id": "co-stg-api",
      "name": "Backend /health (staging)",
      "url": "https://backend-staging-5366.up.railway.app/health",
      "state": "up",
      "status": 200,
      "ttfb": 415,
      "total": 415,
      "edge": "iad1",
      "warnMs": 3000,
      "service": "Catholic Owned — Staging"
    },
    {
      "id": "co-stg-www",
      "name": "Storefront (staging)",
      "url": "https://marketplace-staging-f930.up.railway.app/us",
      "state": "up",
      "status": 200,
      "ttfb": 779,
      "total": 793,
      "edge": "iad1",
      "warnMs": 5000,
      "service": "Catholic Owned — Staging"
    }
  ]
}