{
  "ts": "2026-07-19T18:41:43.421Z",
  "overall": "down",
  "results": [
    {
      "id": "co-www-home",
      "name": "Storefront home",
      "url": "https://www.catholicowned.com/us",
      "state": "up",
      "status": 200,
      "ttfb": 427,
      "total": 448,
      "edge": "iad1",
      "warnMs": 3000,
      "service": "Catholic Owned — Production"
    },
    {
      "id": "co-www-directory",
      "name": "Directory",
      "url": "https://www.catholicowned.com/us/directory",
      "state": "up",
      "status": 200,
      "ttfb": 362,
      "total": 388,
      "edge": "iad1",
      "warnMs": 3000,
      "service": "Catholic Owned — Production"
    },
    {
      "id": "co-api-health",
      "name": "Backend API /health",
      "url": "https://api.catholicowned.com/health",
      "state": "up",
      "status": 200,
      "ttfb": 369,
      "total": 369,
      "edge": "iad1",
      "warnMs": 1500,
      "service": "Catholic Owned — Production"
    },
    {
      "id": "co-admin",
      "name": "Admin dashboard",
      "url": "https://v3-admin.catholicowned.com/",
      "state": "up",
      "status": 200,
      "ttfb": 176,
      "total": 180,
      "edge": "iad1",
      "warnMs": 2000,
      "service": "Catholic Owned — Production"
    },
    {
      "id": "co-vendor",
      "name": "Vendor dashboard",
      "url": "https://v3-vendor.catholicowned.com/",
      "state": "down",
      "status": 502,
      "ttfb": 15242,
      "total": 15242,
      "edge": "iad1",
      "warnMs": 2000,
      "service": "Catholic Owned — Production"
    },
    {
      "id": "co-cdn",
      "name": "Media CDN (minio)",
      "url": "https://v3-cdn.catholicowned.com/",
      "state": "up",
      "status": 403,
      "ttfb": 377,
      "total": 377,
      "edge": "iad1",
      "warnMs": 3000,
      "service": "Catholic Owned — Production"
    },
    {
      "id": "co-stg-api",
      "name": "Backend /health (staging)",
      "url": "https://backend-staging-5366.up.railway.app/health",
      "state": "up",
      "status": 200,
      "ttfb": 458,
      "total": 459,
      "edge": "iad1",
      "warnMs": 3000,
      "service": "Catholic Owned — Staging"
    },
    {
      "id": "co-stg-www",
      "name": "Storefront (staging)",
      "url": "https://marketplace-staging-f930.up.railway.app/us",
      "state": "up",
      "status": 200,
      "ttfb": 686,
      "total": 699,
      "edge": "iad1",
      "warnMs": 5000,
      "service": "Catholic Owned — Staging"
    }
  ]
}