{"co-www":{"lastTs":"2026-07-11T15:16:46.659480166Z","ipsByHour":{"2026-07-11T13":["BpNy8LNz3h","93qPvTdrbm","3e1tqjgvGw","zzN1SDxodM","So37okAZos","iO0-dKj-yZ","4xsn6lkaVr","NFliAqb0WF","IFQJKL7J7x","E4fdSGuLcl","Ixn8iZFASE","8JAtA_-wAG","xPw6XwOccN","aNobE9tpQJ","QYAkeQPuzU","pQfRUNKe-t","1L_Bbf83Xy","1pSj32Edwa","LoJehJz78a","4-ZNQBGJhL","OX61CtiBHb","KX53vWQzpI","nmiEzoDsox","9IWzT3InNq","iR0P0_hoXf","4u46IqJJVl","nVZabGPa5q","vL70IPMGNw","o-ji7kxSWS","iHVpn3ahZA","PXEDXeJaug","00UO8yxQU3","dWD1An4zQb","VlXYIcJ5T0","udsCWcmLTy","8HynyOjj0M","SrlFraDA7K","8LvQ8hFhT5","7FrxXuJVGM","0DAndYUNdn","AObCQ0siP0","MO1HVZumIV","PWbXQsugj-","I0mN6geACv"],"2026-07-11T14":["1pSj32Edwa","qeWwTAVZvZ","1lYsnARRQ6","zzN1SDxodM","XXPzqKjj_r","r-Gf4XfFUg","3e1tqjgvGw","ZO__CElpKf","iO0-dKj-yZ","0DAndYUNdn","0OpATSDPiY","PF5wVQxGLc","4u46IqJJVl","w7doSYV86p","UlpSa_yfID","GU-hkzBIl2","cjvk536FwN","GVwFckYBQA","wQmjAoL5LG","fwve7drO8-","ZYeo2L-IOf","Duhev6xAnC","eNhuwRlMFJ","tMuuDRN55L","Xug6fP2piZ","t3AwxbJdqd","haiYS-ih97","rIkhniivZf","jy1TyahZTc","S07R9BRA2Y","UjrxhD8htB","Pf-vOgsKZO","CBeZdQd__c","tNZX2IGfjh","c0YRchYutd","xXel_1R34W","dkkaVR-L0S","USk774af2Q","HPZn5Bqo1W","udsCWcmLTy","rKycSepemZ","nmiEzoDsox","_32-aQJpdu","IpRWQdViRq","kqgMQQ5HGQ","IFQJKL7J7x","lXZGUh8yeI","BQyQdmjbWD","QgboyZ6jkB"],"2026-07-11T15":["c0YRchYutd","rKycSepemZ","1lYsnARRQ6","1pSj32Edwa","WG39Cg0QNR","P6h0qhOwCC","0DAndYUNdn","t0Wj2fAKr_","3e1tqjgvGw","w7doSYV86p","TIpI34T4uE","QH8o-X7ti3","GYLDKeOsfZ","jhmESSC941","6HUbEP0nAU","XrytlMkzkA","FQIi0Xx61V","9_J99UGdy1","39szmQLPxi"]}}}