{"co-www":{"lastTs":"2026-07-09T02:55:09.144644037Z","ipsByHour":{"2026-07-09T02":["Q-5ESMVprC","8TtckwE-8x","6x03wrau-u","bOWUv1s1DB","pfZftkQlYi","waQMRp4WRR","wa2sex7yqE","IPJ2qVEQdY","T1f9x5gVlF","e5Ko1kDRAo","i4JxBWBOVb","gfVh-j8HQz","_FGHDfnpyG","eSbfnBUIQ4","WE02biKyyU","YDRfHNs6T_","8dV0twjTRm","U6GALe4BCG","sTuj1EQVkl","5KSaab36oM","OFXq9OUv7w","z-B8UBQlfI","99blgpZlc-","wtqcsvn-Eb","Cw4eHTWYKH","mZ2PT9j4j2","vyhFUF4bur","zQ5J7m8d64","XwPAJmJ3Ck","aEg6XS-FbN","tMlCDLsroM","Css3uo8F5R","kzySkOj2IN","KcD9Bc1-0E","M7jbOSoiHH","CkZtBxGU5_","FsAlTBQnU6","7FK1jOOtj_","FBV6LHAFrd","Ixn8iZFASE","8HynyOjj0M","QYAkeQPuzU","8JAtA_-wAG","NFliAqb0WF","xPw6XwOccN","E4fdSGuLcl","2uu3A49uMt","0_0ReinO-G","OeLPGTQITA","WjPzf1W8G5","_9B_i4g5v8","OX61CtiBHb","73HP2eAoc1","vFx4R0dPkv","9dCBm3BNx3","34aCCSse_i","PA-77-Xg9W","E1I_2FcKzh"],"2026-07-09T00":["DrBE4m9qtQ","2Zl29QD2RP","wa2sex7yqE","Ax-F4RFUi-","pfZftkQlYi","IifzAmqrUP","og0LowqDxF","Z3m7iYBoHQ","Bb-lLwO67P","3e1tqjgvGw","Ea1q4aNr0q","0ir7IZPcTK","_9B_i4g5v8","Z_9JWQWM1q","u2DyymVwJI","PAP_hXLfkE","SlRv32y8zP","RRSzRA0i5b","aB2VTRWj5J","zzGgTIFisH","FhepuhLNWN","hvgNIvi1Ia","CqCagGT_GY","Z3GTN4Ef9m","jRGSgF8RX7","toaDK_J6bA","EM4Omlv4bQ","_FGHDfnpyG","wKFucr8BrE","CRyyBgycOq","V3C8U47wbQ","OX61CtiBHb","ZGElMXso3X","9a9nVzhmO5","U6D-CQwj00","haDT5zV4wy","M5jq9DnbsA","hajdDVCQKi","olyH9rrmLF"],"2026-07-09T01":["Z_9JWQWM1q","wa2sex7yqE","pfZftkQlYi","pyJyKlNKRp","Ea1q4aNr0q","Ie7Ml4BRz6","a5_-_-1koa","vpn9yz3ifz","OX61CtiBHb","j0rqee6kHs","KU2RAOb-jw","rC92ZzH1LC","b3IVZ5T-CQ","ZO4khx3EgT","pybtOUwE6I","44_UGT9cHQ","py5m4HOyMw","6OzL5KA2ks","9uI_a1bleG","e49E17rJt4","mZ2PT9j4j2","XKlozhggTC","8dV0twjTRm","jMpk6GJP1K","BkAv88zzo8","HPZn5Bqo1W","r0gTIYkBEV","vCde-D3VqN","9mH8eMeYlm","nMg-15gsCn","nNAZB-_Dzx","u2DyymVwJI","sHfI0hhbBL","CZ9OFGCHwO","Ku_yf-wUb_"]}}}