{"co-www":{"lastTs":"2026-07-17T10:56:20.082025007Z","ipsByHour":{"2026-07-17T08":["Z0qV-HjLkW","oXfFDUvAtj","jDnvdtlyep","Hj_yUpk8De","l5p13Ja7Y_","K5m56ooZDD","IFQJKL7J7x","gbPq9C7rnb","pXOndX9Xwf","rKycSepemZ","ydlmZvBcKG","ccQluaEYfX","zzN1SDxodM","T6B0kLOZ9j","tb3rSuWC66","dkkaVR-L0S","UsEGdpPgSA","bXFlMr9D4k","I0Xtj9dHQH","GlfdqYGu6m","r2Liky2cTb","k_7KavgAQi","1lYsnARRQ6","CvAsaGVKUH","vNaLG8S26h","SW_gIuF3TD","vQ-Lhztt33","Z-OkfRyPYD","DOJgj0ad_g","yAbKMFWjH5","-76Oyj_MYf","n1gt1Ng6Kd","7L-84LP4I8","6DOYgwMWJH","1_IdurBi16","uxHZnUJVab","pyJyKlNKRp","216WYBizuO","Wd9WjoeGDH"],"2026-07-17T09":["8my01F882k","IlYka4od-q","f_gyYp3NBH","dQp976qlhj","YVLo2i9x84","ZeqDuKSTgm","ivAT9M0WRb","CSU3YemnGL","FDBaNRQPq1","X2jUXXGST-","ydlmZvBcKG","w0sfixokVU","5Z3MoBO_da","PtITW-VNWv","ogH_ZErxt-","hp8QJxcXyH","S6lhvHPdTp","VumMzSQgsV","S1MQMPR_QQ","6_Uy3UciZo","UdnIMPCo86","CvAsaGVKUH","mBl9agzG5j","rKycSepemZ","-bW7J3F1hX","u2DyymVwJI","MHdTN3wJkL","xp9RAk0mRz","xx33YtxHiC","KFKYs4GcMi","h3PMYmqneR","mjQjTNt2Cr","UvvAUuY-7d","HJD2ys5WdB","xHgeeOGpxJ","xEesTIbSDP","fjfmBpbwNZ","BkAv88zzo8"],"2026-07-17T10":["qN0JUwWAFb","ydlmZvBcKG","uZMkjnE5kM","ULZJ_gYZhL","dJTv1aszrY","mBl9agzG5j","zzGgTIFisH","FTfifjH431","iUeZm7lRmA","CzKGuaUP-W","Ayu6ESp8JX","Z3iXkdw1Dc","zU-l-YFeZZ","UxqW6mw5zP","SvP8JQk_ch","XbB-nUerAN","lrX_J5iw-D","g5vHTdOtXb","r3vXZzvQNG","zXsdv7pd28","FbCT5L31Lt","sCGx8eRKFE","z91zaydBmI","WIAWsEFjFu","i6n-AZl0TF","OEZieb22lj","OkrRL6wckW","aTptj-iWUt","ci69PVzwfi","-lhcbPniTQ","EijC84nqVn","esZO2W0mo7","dewSJsqO_R","tzznTtx9EH","0RHMKTg0XX","nWWpdS_cMx","HueVDfKnKE","hSq1xbEkok","36f9yuTBnd","F1-SIrh7pA","qQFuSHudO9","g09qnDkHt5","JFDzLHsAUm","q7nuJEUuqk","0OzE3tyeWV","-HKNTiFR4X","530BJ3Muoi","GjafqqdkYA","AyFCe1NkEq","3-XlM2eUOp","WzzqqUfIlI","DoUB2UMybX","VfSaJMiwKI","aUoma8SvX5"]}}}