{"co-www":{"lastTs":"2026-07-22T19:49:49.252290477Z","ipsByHour":{"2026-07-22T17":["YybKCf7hki","eMlVVZUfVR","vSVIwAZYId","qre3qSza39","xgaqmqIkky","jfoRdcSAN8","Ls-0cNXfUz","t0Wj2fAKr_","_AvnBHk-Eh","YN5o-P-7Z-","sVWcUAMUE2","fsLGseRKGX","Cnf8Su7mKY","qeWwTAVZvZ","rKycSepemZ","srr6QPAfLH","bX0ehB48s7","DRzd62v4aw","1y9Y4sK_XX","0nK_mqyL32","pbKwR0kURi","v1ErDiP2-9","0SZFHT86vf","JZ84GC3Amn","f5Wa7OGBff","dK6aiaOqmr","FnykhGdi4z","FQIi0Xx61V","2NFmTk492z","dlunovsaEW","dh1eADmvDu","xZ11EBn8zt","bqCrdBU5U-","nAkXffK7mU","qmFcgPqXxK","jqepy8HDqU","SuV4GHRsmi","ZaKVzitRDU","g3vRWRFR6x","KgehcnjfHN","6k9KSY3f9W","LxH8unfTzG","tmAwDsjrJN","4WOJqK3so9","Q-G5h9tjjr","au5cFlNRuE"],"2026-07-22T18":["FQjiNjvkEf","yV5APn3Z2V","NCAdM8nlWv","6k9KSY3f9W","Tv-dxbQnfE","eMlVVZUfVR","KX53vWQzpI","LbLJn3f4j7","pavPQvLXa-","q4erbascf4","7_SUW9rMsm","VeMOAwIK0o","KgUV1EGbZf","vv2l40Iizm","haDT5zV4wy","zQNbq9wZa8","NkKXfERC0x","vpxwRxFLAe","stKqBD1ntm","q86Ju8vc1m","9DY6816OdA","9dLgwqrYAW","6yMfvLqznG","rq3W_fftDO","h1dhX0WaDz","idOSY6FZ4x","6Ha9OY3M5l","N1xP2KnmkQ","N9kUC-19og","R8Yhe8suLJ","eycEsJLd_Y","Ch5GbI5jMK","QaAnZ_K4tK","enJegTx52r","o2N3QaVS92","Irhl8sIUbS","wAlmMeI09J","jntgqG4w3Q"],"2026-07-22T19":["2mzHMRhH1u","MRKcAv2ITW","whLoyAB3jk","H-qTwhAEIb","RC0rMrBrbe","l60kx_CXV0","r5sh4BkjBQ","ivAT9M0WRb","ZeqDuKSTgm","5dgKd3WLhl","R2702OeLKN","CuUWLrfbPZ","hB988Ieqll","J6HqqDWZZW","MtYaCCCb3J","85DbdGoqeQ","CT8udwhI-M","rvjwTaErc0","GbvMVpWJ-Q","pV2u3ND4m5","oZnhK5L3vO","JfoRKlB82x","9dLgwqrYAW","g4i1CyS9iH","saPEvdEoRf","Gbb1HmpbPA","_0FR5yF1H6","XAMNZP8OLw","Df8TtNfBP5","GnDIxtehdb","ly8KZqJL9z","6HUbEP0nAU","Mp-8xSqJnJ","H7ixhHhYdS","CWtk2XyCc6","WHekaVnj__","D34SaYyBOD","MGGOEfpQAw","bYzL4glEO4","npkAByEYq-","gaypDBFr0f","RairnD_QPc","Hap-buM2Q2","kzj4vJ90NP","Ayu6ESp8JX","6nzjlrXbZn","1By-tVZZtu","ZyAOHDPLum","4pndLb3IKa","KtcI6ih0Mr","yJj5Bfk02Q","55RCv8JvUh","ABapU_0f7A","0pVaFo599U"]}}}