{"co-www":{"lastTs":"2026-07-15T17:34:04.607988467Z","ipsByHour":{"2026-07-15T15":["4g7a4lVe29","kQOnpOCrMl","DYfBDLq-h3","7dKOx887Hp","VI8hcj7Mfv","qNAGAk8h6M","aPBCfkLDP4","zdzuyjCCP6","9n4WC2rWX4","2lcFsHKKhu","siEwznJgKr","ErexW2HCdB","3RjmixoJEV","oBwiA46tEv","Tsp1f4ElBr","p6hvJMegY7","npsjexjcIJ","z5i2tG22AE","9ZV_Iu1Bcd","1pSj32Edwa","3e1tqjgvGw","hQ_7_tQJhB","f8mU5vbscX","XrytlMkzkA","sFCmevim9B","78AftdxXU9","LSH6MpQwSS","TqL36hsLmk","evhgGKfJLv","nSdiVtDb-M","x3QForBsZF","mvm968ZwEa","_mdW4EalKZ","C1wrSTB88r","qIsqSHRQeB","b8y_MMfAMg","G0CzLMVuVQ","cBOpgmW_J-","m27zC2zOho","UPTWgp18Fa","xxhGN4ufIQ","mY4ZCG352B","5R8iuVkoLF","vyBuFxAhSk","IpRWQdViRq","Hui9SWSF39","peIVmc586_","TOzufh5ySU","Ll0RgPiFQU","VzY2uCdJCu","wJ_hZn0zLu","Qy7YHS58XW","74XOdl4tZq","JjN2bDNa7n","eVmfE8uU63","_0FR5yF1H6","Ej0JYBAICC","lkw28gKM1H","FbvLvhj8do","QldcZLZqHs","mbNWu9rivT","mZ52sB0uhj","QtnIiPMI07","lYOBK9pIyR","TEXR78py0K","Jc_UCAlbN4","BnOt_L3mxo","Oe5_0fHkQx","xT9qDhBmyU","J1WRJzdM8p","OrmPyaaQUg","VewzXY1Gtm","nO-7kY6tKv","IFCaPubJyq","_S69xBJxwJ","M9dKj3sMFs","hTZt99_8gh","YB94bdRNoR","u_ZHQFuZLC","-bW7J3F1hX","9dLgwqrYAW","x1nO4L3X9k","WIAWsEFjFu","AiCjcit2xl","XmkSFSDqCJ","icqsJN6EOq","Vcev89_1Is","HhqWXUFpMt","85DbdGoqeQ","7cfYjQgREr","Wpylt-fqeW","XxGmTwkEKO","1IqCXU6Eyh","SAUqKj8MJ5","OX61CtiBHb","GlfdqYGu6m","TBPNEWb4M_","8On3ye6AQ_","TustBJ5fZg","rw9qYJYkw6"],"2026-07-15T16":["ErexW2HCdB","IORZv7J45x","3e1tqjgvGw","Bm7x9eK5OV","N5WI0NLbx9","jGZVSxJ15T","UjrxhD8htB","1pSj32Edwa","j-2vhksYix","VzVbq6uJkE","XMfv5wOosO","XrytlMkzkA","Mp-8xSqJnJ","8dqxD3rZ4h","-Bg2sgNuQr","At8TreUVO0","Q-X_Q4Bk7q","ELeySogFXY","Wdq0RssNty","_8N5DXr8rU","G54_zRGZPk","0wFmrUtfGQ","9_NLH-HP6E","ZYeo2L-IOf","y1ekjNp9kS","ud4OiymoLM","kQOnpOCrMl","up9TJ01UG7","cxX2he8Mk3","HG5LZMtVIe","PXEDXeJaug","00UO8yxQU3","iHVpn3ahZA","pnNCPqBRw3","MPH8GM630U","V79GjHMlhH","IRyrdN0jbN","jRJ_mY1uAd","KySpo6PAKs","vUu5FP7rSz","uihTLy9nKB","980yCQjXp4","_8RxlDk752","7Tq2R4i_ip","YnD9DhfN4a","CX_pbbqEEa","E6LFL6dNNB","FmUzffrbB-","f0SWMOk27V","5G4mmVhTRP","dR8q_gdL35","F0TwSU3suE","L6iyAktti1","5CQN0qlk5_","lTxdd0N0Aa","WNXoTlJJg8","H3qv_UrcSp","JE-gBP2Afo","n-HB5HRQU-","lsasriuiSv","jQNzhJPAnV","_Pxpaa_OuK","8CTpMeXmdg","T2Of563NEW","FYCx9ZBa07","oMVaUMu9q4","u2DyymVwJI","_q0rawCWnT","yAceckGYcM","Juw-U70B1a","Gx3WGv5tlr","tjVjnN2WQr","a9hNOUqbim","KRqpAYTIlS","E3aydiG7FK","EVhWjJ8Z6a","JSkkL5e5Tk","kJpOnQyjk9","o2N3QaVS92","5p7Cg3pP8n","mk9zfiWzwM","KGI0Ot9_MF","4bWfdbxwFU","I1Jrj4-zVj","nHFa0e1AVA","hi4EGh9QrE","LlEDCUurPt","Jvs3xYLDkC","0D8fVKcCNp","R1s9T6UO9P","tg_xhlx4VK","etjRNjVMkl","g88cq7KWRS","4zefTkX_ui","7xzzoSA__D","eEcLHeIQW7","SHSHOM881y","3Lr8yYKE68","Durt0W-P8k","AlQN283CP0","SAtmMJJ-K0","MJG5ohmjUb","JFjpR2QHw0"],"2026-07-15T17":["xsQrSR6uqX","ErexW2HCdB","3e1tqjgvGw","8lpZhluLxo","ijMl_QNcxc","HwvuLMcRZ1","ITAq3fYbjR","uWkrteRX7N","kfV3hOIVAs","4JSlrpEkA-","hy2S-28ZKN","XwHVkE3Ua5","HawdCL_ixI","2d14pqt-T4","_49TzvRF3e","SZn78k8Tne","T2Of563NEW","FJvTbCRlfO","A80SSz2MSN","xuQ4EzM9EC","W4NdqOXlCc","DCI86bUivM","xkXf9jdAzD","Ke7HR0xJwJ","FDBaNRQPq1","yuqeAEkjuZ","uEfqPvmkag","3Vl51I32ra","5TeDxhTdPk","xVje600XWC","rJKk1Bdxch","3K89-qAdMn","fRK2veL3gY","T9zpcnuTGG","2Ack_S_27C","ulwYHkV362","lfWO7FVwIJ","dmWnS_lVGp","nbUfmrbMGi","CYprYaigfp","QgEbdoxwT6","tIED5Od_h_","Dc6q2F51K0","9wnuW_E9t0","rFPxYR8V4V","LvDzx4GNQ7","RxsKdOB20G","4jPXpNc0fi","a5i1uN9-vW"]}}}